verilog/rtl/format_convert.v
`default_nettype none

module format_convert(
    input wire mode_12, // 1 for 12 hour mode, 0 for 24 hour mode
    input wire [3:0] hr_tens_24,
    input wire [3:0] hr_ones_24,

    output reg [3:0] hr_tens_12,
    output reg [3:0] hr_ones_12,
    output reg am_pm // 1 for PM, 0 for AM
  );
  wire [4:0] hour24 = (hr_tens_24 * 4'd10)+ hr_ones_24;
  wire[4:0] hour12 = (hour24
                      == 5'd0)?5'd12: (hour24>5'd12)?(hour24-5'd12):hour24;
  always@(*)
  begin
    if(mode_12 == 1'b1)
    begin
      am_pm = (hour24 >= 5'd12);
      hr_tens_12 = (hour12 >= 5'd10) ? 4'd1 : 4'd0;
      hr_ones_12 = (hour12 >= 5'd10) ? (hour12 - 5'd10) : hour12;
    end
    else
    begin
      hr_tens_12 = hr_tens_24;
      hr_ones_12 = hr_ones_24;
      am_pm = 1'b0;

    end
  end
endmodule
`default_nettype wire

verilog/tb/tb_format_convert.v
`timescale 1ns/1ps

module tb_format_convert;

  //----------------------------------------------------------------
  // Signals
  //----------------------------------------------------------------
  reg        mode_12;
  reg  [3:0] hr_tens_24;
  reg  [3:0] hr_ones_24;

  wire [3:0] hr_tens_12;
  wire [3:0] hr_ones_12;
  wire       am_pm;

  integer h;
  integer errors = 0;

  //----------------------------------------------------------------
  // Device under test
  //----------------------------------------------------------------
  format_convert dut (
                   .mode_12    (mode_12),
                   .hr_tens_24 (hr_tens_24),
                   .hr_ones_24 (hr_ones_24),
                   .hr_tens_12 (hr_tens_12),
                   .hr_ones_12 (hr_ones_12),
                   .am_pm      (am_pm)
                 );

  //----------------------------------------------------------------
  // Check task. Compares actual against expected and counts errors.
  //----------------------------------------------------------------
  task check;
    input [4:0] exp_hour;
    input       exp_pm;
    reg   [4:0] got_hour;
    begin
      got_hour = (hr_tens_12 * 4'd10) + hr_ones_12;
      if (got_hour !== exp_hour || am_pm !== exp_pm)
      begin
        $display("  MISMATCH  expected %0d pm=%b  got %0d pm=%b",
                 exp_hour, exp_pm, got_hour, am_pm);
        errors = errors + 1;
      end
    end
  endtask

  //----------------------------------------------------------------
  // Stimulus
  //----------------------------------------------------------------
  initial
  begin
    $dumpfile("format.vcd");
    $dumpvars(0, tb_format_convert);

    //------------------------------------------------------------
    // 12 hour mode, all 24 inputs
    //------------------------------------------------------------
    $display("=== 12 hour mode ===");
    mode_12 = 1'b1;

    for (h = 0; h < 24; h = h + 1)
    begin
      hr_tens_24 = h / 10;
      hr_ones_24 = h % 10;
      #10;

      $display("24h=%2d  ->  %0d%0d  %s",
               h, hr_tens_12, hr_ones_12, am_pm ? "PM" : "AM");

      if (h == 0)
        check(5'd12, 1'b0);
      else if (h < 12)
        check(h[4:0], 1'b0);
      else if (h == 12)
        check(5'd12, 1'b1);
      else
        check(h[4:0] - 5'd12, 1'b1);
    end

    //------------------------------------------------------------
    // 24 hour mode, digits must pass through unchanged
    //------------------------------------------------------------
    $display("=== 24 hour mode ===");
    mode_12 = 1'b0;

    for (h = 0; h < 24; h = h + 1)
    begin
      hr_tens_24 = h / 10;
      hr_ones_24 = h % 10;
      #10;

      $display("24h=%2d  ->  %0d%0d",
               h, hr_tens_12, hr_ones_12);

      check(h[4:0], am_pm);   // value must match, pm ignored here
    end

    //------------------------------------------------------------
    // Verdict
    //------------------------------------------------------------
    if (errors == 0)
      $display("PASS, all 48 cases correct");
    else
      $display("FAIL, %0d mismatches", errors);

    $finish;
  end

endmodule

verilog/format.vcd
$date
	Sun Sep  6 19:12:26 2026
$end
$version
	Icarus Verilog
$end
$timescale
	1ps
$end
$scope module tb_format_convert $end
$var wire 4 ! hr_tens_12 [3:0] $end
$var wire 4 " hr_ones_12 [3:0] $end
$var wire 1 # am_pm $end
$var reg 4 $ hr_ones_24 [3:0] $end
$var reg 4 % hr_tens_24 [3:0] $end
$var reg 1 & mode_12 $end
$var integer 32 ' errors [31:0] $end
$var integer 32 ( h [31:0] $end
$scope module dut $end
$var wire 4 ) hr_ones_24 [3:0] $end
$var wire 4 * hr_tens_24 [3:0] $end
$var wire 1 & mode_12 $end
$var wire 5 + hour24 [4:0] $end
$var wire 5 , hour12 [4:0] $end
$var reg 1 # am_pm $end
$var reg 4 - hr_ones_12 [3:0] $end
$var reg 4 . hr_tens_12 [3:0] $end
$upscope $end
$scope task check $end
$var reg 5 / exp_hour [4:0] $end
$var reg 1 0 exp_pm $end
$var reg 5 1 got_hour [4:0] $end
$upscope $end
$upscope $end
$enddefinitions $end
$comment Show the parameter values. $end
$dumpall
$end
#0
$dumpvars
bx 1
x0
bx /
b1 .
b10 -
b1100 ,
b0 +
b0 *
b0 )
b0 (
b0 '
1&
b0 %
b0 $
0#
b10 "
b1 !
$end
#10000
b1 "
b1 -
b0 !
b0 .
b1 ,
b1 +
b1 $
b1 )
b1 (
b1100 1
00
b1100 /
#20000
b10 "
b10 -
b10 ,
b10 +
b10 $
b10 )
b10 (
b1 1
b1 /
#30000
b11 "
b11 -
b11 ,
b11 +
b11 $
b11 )
b11 (
b10 1
b10 /
#40000
b100 "
b100 -
b100 ,
b100 +
b100 $
b100 )
b100 (
b11 1
b11 /
#50000
b101 "
b101 -
b101 ,
b101 +
b101 $
b101 )
b101 (
b100 1
b100 /
#60000
b110 "
b110 -
b110 ,
b110 +
b110 $
b110 )
b110 (
b101 1
b101 /
#70000
b111 "
b111 -
b111 ,
b111 +
b111 $
b111 )
b111 (
b110 1
b110 /
#80000
b1000 "
b1000 -
b1000 ,
b1000 +
b1000 $
b1000 )
b1000 (
b111 1
b111 /
#90000
b1001 "
b1001 -
b1001 ,
b1001 +
b1001 $
b1001 )
b1001 (
b1000 1
b1000 /
#100000
b0 "
b0 -
b1 !
b1 .
b1010 ,
0#
b1010 +
b0 $
b0 )
b1 %
b1 *
b1010 (
b1001 1
b1001 /
#110000
b1 "
b1 -
b1011 ,
b1011 +
b1 $
b1 )
b1011 (
b1010 1
b1010 /
#120000
b10 "
b10 -
b1100 ,
1#
b1100 +
b10 $
b10 )
b1100 (
b1011 1
b1011 /
#130000
b1 "
b1 -
b0 !
b0 .
b1 ,
b1101 +
b11 $
b11 )
b1101 (
b1100 1
10
b1100 /
#140000
b10 "
b10 -
b10 ,
b1110 +
b100 $
b100 )
b1110 (
b1 1
b1 /
#150000
b11 "
b11 -
b11 ,
b1111 +
b101 $
b101 )
b1111 (
b10 1
b10 /
#160000
b100 "
b100 -
b100 ,
b10000 +
b110 $
b110 )
b10000 (
b11 1
b11 /
#170000
b101 "
b101 -
b101 ,
b10001 +
b111 $
b111 )
b10001 (
b100 1
b100 /
#180000
b110 "
b110 -
b110 ,
b10010 +
b1000 $
b1000 )
b10010 (
b101 1
b101 /
#190000
b111 "
b111 -
b111 ,
b10011 +
b1001 $
b1001 )
b10011 (
b110 1
b110 /
#200000
b1000 "
b1000 -
b1000 ,
b10100 +
b0 $
b0 )
b10 %
b10 *
b10100 (
b111 1
b111 /
#210000
b1001 "
b1001 -
b1001 ,
b10101 +
b1 $
b1 )
b10101 (
b1000 1
b1000 /
#220000
b0 "
b0 -
b1 !
b1 .
b1010 ,
b10110 +
b10 $
b10 )
b10110 (
b1001 1
b1001 /
#230000
b1 "
b1 -
b1011 ,
b10111 +
b11 $
b11 )
b10111 (
b1010 1
b1010 /
#240000
b1100 ,
b0 +
0#
b0 "
b0 -
b0 !
b0 .
b0 $
b0 )
b0 %
b0 *
0&
b0 (
b1011 1
b1011 /
#250000
b1 ,
b1 "
b1 -
b1 +
b1 $
b1 )
b1 (
b0 1
00
b0 /
#260000
b10 ,
b10 "
b10 -
b10 +
b10 $
b10 )
b10 (
b1 1
b1 /
#270000
b11 ,
b11 "
b11 -
b11 +
b11 $
b11 )
b11 (
b10 1
b10 /
#280000
b100 ,
b100 "
b100 -
b100 +
b100 $
b100 )
b100 (
b11 1
b11 /
#290000
b101 ,
b101 "
b101 -
b101 +
b101 $
b101 )
b101 (
b100 1
b100 /
#300000
b110 ,
b110 "
b110 -
b110 +
b110 $
b110 )
b110 (
b101 1
b101 /
#310000
b111 ,
b111 "
b111 -
b111 +
b111 $
b111 )
b111 (
b110 1
b110 /
#320000
b1000 ,
b1000 "
b1000 -
b1000 +
b1000 $
b1000 )
b1000 (
b111 1
b111 /
#330000
b1001 ,
b1001 "
b1001 -
b1001 +
b1001 $
b1001 )
b1001 (
b1000 1
b1000 /
#340000
b1010 ,
b0 "
b0 -
b1 !
b1 .
b1010 +
b0 $
b0 )
b1 %
b1 *
b1010 (
b1001 1
b1001 /
#350000
b1011 ,
b1 "
b1 -
b1011 +
b1 $
b1 )
b1011 (
b1010 1
b1010 /
#360000
b1100 ,
b10 "
b10 -
b1100 +
b10 $
b10 )
b1100 (
b1011 1
b1011 /
#370000
b1 ,
b11 "
b11 -
b1101 +
b11 $
b11 )
b1101 (
b1100 1
b1100 /
#380000
b10 ,
b100 "
b100 -
b1110 +
b100 $
b100 )
b1110 (
b1101 1
b1101 /
#390000
b11 ,
b101 "
b101 -
b1111 +
b101 $
b101 )
b1111 (
b1110 1
b1110 /
#400000
b100 ,
b110 "
b110 -
b10000 +
b110 $
b110 )
b10000 (
b1111 1
b1111 /
#410000
b101 ,
b111 "
b111 -
b10001 +
b111 $
b111 )
b10001 (
b10000 1
b10000 /
#420000
b110 ,
b1000 "
b1000 -
b10010 +
b1000 $
b1000 )
b10010 (
b10001 1
b10001 /
#430000
b111 ,
b1001 "
b1001 -
b10011 +
b1001 $
b1001 )
b10011 (
b10010 1
b10010 /
#440000
b1000 ,
b0 "
b0 -
b10 !
b10 .
b10100 +
b0 $
b0 )
b10 %
b10 *
b10100 (
b10011 1
b10011 /
#450000
b1001 ,
b1 "
b1 -
b10101 +
b1 $
b1 )
b10101 (
b10100 1
b10100 /
#460000
b1010 ,
b10 "
b10 -
b10110 +
b10 $
b10 )
b10110 (
b10101 1
b10101 /
#470000
b1011 ,
b11 "
b11 -
b10111 +
b11 $
b11 )
b10111 (
b10110 1
b10110 /
#480000
b11000 (
b10111 1
b10111 /
